MANIFEST.in
README.rst
setup.py
grvlms/__about__.py
grvlms/__init__.py
grvlms/config.py
grvlms/env.py
grvlms/exceptions.py
grvlms/firebase_rdb.py
grvlms/fmt.py
grvlms/images.py
grvlms/interactive.py
grvlms/plugins.py
grvlms/scripts.py
grvlms/serialize.py
grvlms/utils.py
grvlms/commands/__init__.py
grvlms/commands/android.py
grvlms/commands/cli.py
grvlms/commands/compose.py
grvlms/commands/config.py
grvlms/commands/context.py
grvlms/commands/dev.py
grvlms/commands/docker.py
grvlms/commands/images.py
grvlms/commands/k8s.py
grvlms/commands/local.py
grvlms/commands/plugins.py
grvlms/commands/ui.py
grvlms/commands/webui.py
grvlms/templates/config.yml
grvlms/templates/kustomization.yml
grvlms/templates/version
grvlms/templates/android/edx.properties
grvlms/templates/android/gradle.properties
grvlms/templates/android/tutor.yaml
grvlms/templates/apps/mysql/auth.env
grvlms/templates/apps/nginx/_grvlms.conf
grvlms/templates/apps/nginx/cms.conf
grvlms/templates/apps/nginx/extra.conf
grvlms/templates/apps/nginx/lms.conf
grvlms/templates/apps/openedx/config/cms.auth.json
grvlms/templates/apps/openedx/config/cms.env.json
grvlms/templates/apps/openedx/config/lms.auth.json
grvlms/templates/apps/openedx/config/lms.env.json
grvlms/templates/apps/openedx/config/lms.yml
grvlms/templates/apps/openedx/config/partials/auth.json
grvlms/templates/apps/openedx/settings/cms/__init__.py
grvlms/templates/apps/openedx/settings/cms/development.py
grvlms/templates/apps/openedx/settings/cms/production.py
grvlms/templates/apps/openedx/settings/lms/__init__.py
grvlms/templates/apps/openedx/settings/lms/development.py
grvlms/templates/apps/openedx/settings/lms/production.py
grvlms/templates/apps/openedx/settings/partials/common_all.py
grvlms/templates/apps/openedx/settings/partials/common_cms.py
grvlms/templates/apps/openedx/settings/partials/common_lms.py
grvlms/templates/build/android/Dockerfile
grvlms/templates/build/android/edx.properties
grvlms/templates/build/forum/Dockerfile
grvlms_openedx.egg-info/PKG-INFO
grvlms_openedx.egg-info/SOURCES.txt
grvlms_openedx.egg-info/dependency_links.txt
grvlms_openedx.egg-info/entry_points.txt
grvlms_openedx.egg-info/requires.txt
grvlms_openedx.egg-info/top_level.txt
